ai2_olmo_core-2.3.0.dist-info/licenses/LICENSE
olmo_core/__init__.py
olmo_core/aliases.py
olmo_core/config.py
olmo_core/doc_utils.py
olmo_core/exceptions.py
olmo_core/io.py
olmo_core/model_ladder.py
olmo_core/py.typed
olmo_core/script_utils.py
olmo_core/utils.py
olmo_core/version.py
olmo_core/data/__init__.py
olmo_core/data/collator.py
olmo_core/data/data_loader.py
olmo_core/data/numpy_dataset.py
olmo_core/data/source_mixture.py
olmo_core/data/tokenizer.py
olmo_core/data/types.py
olmo_core/data/utils.py
olmo_core/data/mixes/OLMo-mix-0625-150Bsample.txt
olmo_core/data/mixes/OLMo-mix-0625-700Bsample.txt
olmo_core/data/mixes/OLMo-mix-0625.txt
olmo_core/data/mixes/OLMo-mix-0925.txt
olmo_core/data/mixes/OLMoE-mix-0824.txt
olmo_core/data/mixes/__init__.py
olmo_core/data/mixes/dolma17.txt
olmo_core/data/mixes/v3-small-ppl-validation.txt
olmo_core/distributed/__init__.py
olmo_core/distributed/utils.py
olmo_core/distributed/checkpoint/__init__.py
olmo_core/distributed/checkpoint/filesystem.py
olmo_core/distributed/parallel/__init__.py
olmo_core/distributed/parallel/context_parallel.py
olmo_core/distributed/parallel/data_parallel.py
olmo_core/distributed/parallel/expert_parallel.py
olmo_core/distributed/parallel/pipeline_parallel.py
olmo_core/distributed/parallel/tensor_parallel.py
olmo_core/eval/__init__.py
olmo_core/eval/evaluator.py
olmo_core/eval/lm_evaluator.py
olmo_core/eval/metrics.py
olmo_core/eval/task_groups.py
olmo_core/float8/__init__.py
olmo_core/float8/ao.py
olmo_core/float8/utils.py
olmo_core/generate/__init__.py
olmo_core/generate/sampling.py
olmo_core/generate/utils.py
olmo_core/generate/generation_module/__init__.py
olmo_core/generate/generation_module/config.py
olmo_core/generate/generation_module/generation_module.py
olmo_core/generate/generation_module/transformer/__init__.py
olmo_core/generate/generation_module/transformer/config.py
olmo_core/generate/generation_module/transformer/generation_module.py
olmo_core/internal/__init__.py
olmo_core/internal/common.py
olmo_core/internal/cookbook.py
ai2_olmo_core-2.3.0.dist-info/METADATA
ai2_olmo_core-2.3.0.dist-info/WHEEL
ai2_olmo_core-2.3.0.dist-info/top_level.txt
ai2_olmo_core-2.3.0.dist-info/RECORD
